ini_config_parser
